dj_loguru/__init__.py
dj_loguru/admin.py
dj_loguru/apps.py
dj_loguru/handlers.py
dj_loguru/loggers.py
dj_loguru/models.py
dj_loguru/tests.py
dj_loguru/utils.py
dj_loguru/views.py
dj_loguru/middlewares/__init__.py
dj_loguru/middlewares/request_log_middleware.py
dj_loguru-0.2.2.dist-info/LICENSE
dj_loguru-0.2.2.dist-info/METADATA
dj_loguru-0.2.2.dist-info/WHEEL
dj_loguru-0.2.2.dist-info/top_level.txt
dj_loguru-0.2.2.dist-info/RECORD
