Metadata-Version: 2.1
Name: dj-loguru
Version: 0.2.2
Summary: Use loguru in Django.
Home-page: https://github.com/lingfromSh/django-loguru
Author: Stephen Ling
Author-email: lingfromsh@163.com
License: MIT
Keywords: Django,loguru
Platform: UNKNOWN
Classifier: Development Status :: 2 - Pre-Alpha
Classifier: Framework :: Django :: 3.2
Classifier: Intended Audience :: Developers
Classifier: License :: OSI Approved :: MIT License
Classifier: Topic :: Software Development :: Libraries
Classifier: Programming Language :: Python :: 3.8
Classifier: Programming Language :: Python :: 3.9
Classifier: Programming Language :: Python :: 3.10
Requires-Python: >=3.8
License-File: LICENSE
Requires-Dist: loguru (>=0.5.3)
Requires-Dist: Django (>=3.2)
